{"book_names": {"gen": "G\u00e9nesis", "exod": "\u00c9xodo", "lev": "Lev\u00edtico", "num": "N\u00fameros", "deut": "Deuteronomio", "josh": "Josu\u00e9", "judg": "Jueces", "ruth": "Rut", "1sam": "1 Samuel", "2sam": "2 Samuel", "1kgs": "1 Reyes", "2kgs": "2 Reyes", "1chr": "1 Cr\u00f3nicas", "2chr": "2 Cr\u00f3nicas", "ezra": "Esdras", "neh": "Nehem\u00edas", "esth": "Ester", "job": "Job", "ps": "Salmos", "prov": "Proverbios", "eccl": "Eclesiast\u00e9s", "song": "Cantares", "isa": "Isa\u00edas", "jer": "Jerem\u00edas", "lam": "Lamentaciones", "ezek": "Ezequiel", "dan": "Daniel", "hos": "Oseas", "joel": "Joel", "amos": "Am\u00f3s", "obad": "Abd\u00edas", "jonah": "Jon\u00e1s", "mic": "Miqueas", "nah": "Nah\u00fam", "hab": "Habacuc", "zeph": "Sofon\u00edas", "hag": "Hageo", "zech": "Zacar\u00edas", "mal": "Malaqu\u00edas", "matt": "Mateo", "mark": "Marcos", "luke": "Lucas", "john": "Juan", "acts": "Hechos", "rom": "Romanos", "1cor": "1 Corintios", "2cor": "2 Corintios", "gal": "G\u00e1latas", "eph": "Efesios", "phil": "Filipenses", "col": "Colosenses", "1thess": "1 Tesalonicenses", "2thess": "2 Tesalonicenses", "1tim": "1 Timoteo", "2tim": "2 Timoteo", "titus": "Tito", "phlm": "Filem\u00f3n", "heb": "Hebreos", "jas": "Santiago", "1pet": "1 Pedro", "2pet": "2 Pedro", "1john": "1 Juan", "2john": "2 Juan", "3john": "3 Juan", "jude": "Judas", "rev": "Apocalipsis"}, "chapter_titles": {"gen": {"1": "La creaci\u00f3n", "2": "El hombre en el huerto de Ed\u00e9n", "3": "Desobediencia del hombre", "4": "Ca\u00edn y Abel", "5": "Los descendientes de Ad\u00e1n", "6": "La maldad de los hombres", "7": "El diluvio", "8": "Pero Dios se acord\u00f3 de No\u00e9, y de todos los animales y bestias que estaban en el ", "9": "Pacto de Dios con No\u00e9", "10": "Los descendientes de los hijos de No\u00e9", "11": "La torre de Babel", "12": "Dios llama a Abr\u00e1n", "13": "Abr\u00e1n y Lot se separan", "14": "Abr\u00e1n liberta a Lot", "15": "Dios promete a Abr\u00e1n un hijo", "16": "Agar e Ismael", "17": "La circuncisi\u00f3n, se\u00f1al del pacto", "18": "Promesa del nacimiento de Isaac", "19": "Destrucci\u00f3n de Sodoma y Gomorra", "20": "Abrah\u00e1n y Abimelec", "21": "Nacimiento de Isaac", "22": "Dios ordena a Abrah\u00e1n sacrificar a Isaac", "23": "Muerte y sepultura de Sara", "24": "Abrah\u00e1n busca esposa para Isaac", "25": "Los descendientes de Abrah\u00e1n y Cetura", "26": "Isaac en Gerar", "27": "Jacob recibe la bendici\u00f3n de Isaac", "28": "Dios se aparece a Jacob en Betel", "29": "Jacob sirve a Lab\u00e1n por Raquel y Lea", "30": "Tretas de Jacob y de Lab\u00e1n", "31": "Jacob huye de Lab\u00e1n", "32": "Jacob se prepara para el encuentro con Esa\u00fa", "33": "Reconciliaci\u00f3n entre Jacob y Esa\u00fa", "34": "La deshonra de Dina vengada", "35": "Dios bendice a Jacob en Betel", "36": "Los descendientes de Esa\u00fa", "37": "Jos\u00e9 es vendido por sus hermanos", "38": "Jud\u00e1 y Tamar", "39": "Jos\u00e9 y la esposa de Potifar", "40": "Jos\u00e9 interpreta dos sue\u00f1os", "41": "Jos\u00e9 interpreta el sue\u00f1o de Fara\u00f3n", "42": "Los hermanos de Jos\u00e9 llegan a Egipto", "43": "Los hermanos de Jos\u00e9 regresan con Benjam\u00edn", "44": "La copa de Jos\u00e9", "45": "Jos\u00e9 se da a conocer a sus hermanos", "46": "Jacob y su familia en Egipto", "47": "Jos\u00e9 fue y le dio la noticia al fara\u00f3n. Le dijo:", "48": "Jacob bendice a Efra\u00edn y a Manas\u00e9s", "49": "Profec\u00eda de Jacob acerca de sus hijos", "50": "Muerte de Jos\u00e9"}, "exod": {"1": "Aflicci\u00f3n de los israelitas en Egipto", "2": "Nacimiento de Mois\u00e9s", "3": "Llamamiento de Mois\u00e9s", "4": "Mois\u00e9s vuelve a Egipto", "5": "Mois\u00e9s y Aar\u00f3n ante el fara\u00f3n", "6": "El Se\u00f1or respondi\u00f3 a Mois\u00e9s:", "7": "La vara de Aar\u00f3n", "8": "La plaga de ranas", "9": "La plaga en el ganado", "10": "La plaga de langostas", "11": "La muerte de los primog\u00e9nitos egipcios", "12": "La Pascua", "13": "Consagraci\u00f3n de los primog\u00e9nitos", "14": "Los israelitas cruzan el Mar Rojo", "15": "C\u00e1ntico de Mois\u00e9s y de Mar\u00eda", "16": "Dios da el man\u00e1", "17": "El agua de la roca", "18": "Jetro visita a Mois\u00e9s", "19": "Israel en el monte Sina\u00ed", "20": "Los Diez Mandamientos", "21": "Leyes para los esclavos", "22": "Leyes para la restituci\u00f3n", "23": "Las tres fiestas anuales", "24": "Mois\u00e9s y los ancianos en el Monte Sina\u00ed", "25": "La ofrenda para el tabern\u00e1culo", "26": "El tabern\u00e1culo", "27": "El altar de bronce", "28": "Las vestiduras de los sacerdotes", "29": "Consagraci\u00f3n de Aar\u00f3n y de sus hijos", "30": "El altar del incienso", "31": "Llamamiento de Besalel y de Aholiab", "32": "Al ver el pueblo que Mois\u00e9s tardaba en bajar del monte, fueron a ver a Aar\u00f3n y l", "33": "Dios promete estar presente", "34": "El pacto renovado", "35": "Reglas para el d\u00eda de reposo", "36": "Se suspende la ofrenda", "37": "Mobiliario del tabern\u00e1culo", "38": "El atrio del tabern\u00e1culo", "39": "Se hacen las vestiduras sacerdotales", "40": "Mois\u00e9s erige el tabern\u00e1culo"}, "lev": {"1": "Los holocaustos", "2": "Las ofrendas", "3": "Ofrendas de paz", "4": "Ofrendas por el pecado", "5": "Ofrendas expiatorias", "6": "Leyes de los sacrificios", "7": "\u00bb\u00c9sta es la ley del sacrificio por la culpa. Se trata de una ofrenda muy santa.", "8": "Consagraci\u00f3n de Aar\u00f3n y de sus hijos", "9": "Los sacrificios de Aar\u00f3n", "10": "El pecado de Nadab y Abi\u00fa", "11": "Animales limpios e impuros", "12": "La purificaci\u00f3n de la mujer despu\u00e9s del parto", "13": "Leyes acerca de la lepra", "14": "El Se\u00f1or habl\u00f3 con Mois\u00e9s, y le dijo:", "15": "Impurezas f\u00edsicas", "16": "El d\u00eda de la expiaci\u00f3n", "17": "El santuario \u00fanico", "18": "Actos prohibidos", "19": "Leyes de santidad y de justicia", "20": "Penas por actos de inmoralidad", "21": "Santidad de los sacerdotes", "22": "Santidad de las ofrendas", "23": "Las fiestas solemnes", "24": "Aceite para las l\u00e1mparas", "25": "El a\u00f1o de reposo y el a\u00f1o del jubileo", "26": "Bendiciones de la obediencia", "27": "Consagraci\u00f3n y rescate [ a ]"}, "num": {"1": "Censo de Israel en Sina\u00ed", "2": "Campamentos y jefes de las tribus", "3": "Censo y deberes de los levitas", "4": "Tareas de los levitas", "5": "Todo impuro es echado fuera del campamento", "6": "El voto de los nazareos", "7": "Ofrendas para la consagraci\u00f3n del altar", "8": "Aar\u00f3n enciende las l\u00e1mparas", "9": "Celebraci\u00f3n de la pascua", "10": "Las trompetas de plata", "11": "El Se\u00f1or env\u00eda codornices", "12": "Murmuraciones contra Mois\u00e9s", "13": "Misi\u00f3n de los doce esp\u00edas", "14": "Rebeli\u00f3n de los israelitas", "15": "Leyes sobre las ofrendas", "16": "La rebeli\u00f3n de Cor\u00e9", "17": "La vara de Aar\u00f3n", "18": "La porci\u00f3n de sacerdotes y levitas", "19": "Purificaci\u00f3n de los impuros", "20": "Agua de la roca", "21": "El rey de Arad ataca a Israel", "22": "Balac manda llamar a Balaam", "23": "Balaam le dijo a Balac:", "24": "Profec\u00eda de Balaam", "25": "Israel acude a Baal Pegor", "26": "Censo del pueblo en Moab", "27": "Las hijas de Selofejad", "28": "Las ofrendas diarias", "29": "\u00bbEl d\u00eda primero del mes s\u00e9ptimo har\u00e1n sonar las trompetas y celebrar\u00e1n una convo", "30": "Ley de los votos", "31": "Venganza de Israel contra Madi\u00e1n", "32": "Propiedad familiar de Rub\u00e9n y Gad", "33": "De Egipto a Edom", "34": "El Se\u00f1or habl\u00f3 con Mois\u00e9s, y le dijo:", "35": "Ciudades de los levitas", "36": "Ley del casamiento de las herederas"}, "deut": {"1": "Mois\u00e9s en la ribera oriental del Jord\u00e1n", "2": "Los a\u00f1os en el desierto", "3": "Israel derrota al rey de Bas\u00e1n", "4": "Mois\u00e9s exhorta a la obediencia", "5": "Los Diez Mandamientos", "6": "El gran mandamiento", "7": "Advertencias contra la idolatr\u00eda", "8": "La buena tierra que han de poseer", "9": "Dios promete destruir a los pueblos cananeos", "10": "El pacto renovado", "11": "La grandeza del Se\u00f1or", "12": "El santuario \u00fanico", "13": "\u00bbCuando en medio de ti surja alg\u00fan profeta, o so\u00f1ador visionario, y te anuncie s", "14": "Animales limpios e inmundos", "15": "La condonaci\u00f3n de deudas", "16": "Fiestas anuales", "17": "Instrucciones acerca del rey", "18": "Derechos de los levitas", "19": "Las ciudades de refugio", "20": "Leyes para la guerra", "21": "Homicidios sin autor evidente", "22": "Leyes sobre la castidad", "23": "Restricciones expresas", "24": "\u00bbCuando alguien tome una mujer y se case con ella, si despu\u00e9s no le agrada por h", "25": "Orden de exterminar a Amalec", "26": "Primicias y diezmos", "27": "La ley inscrita en el monte Ebal", "28": "Bendiciones de la obediencia", "29": "El pacto en Moab", "30": "Condiciones para la restauraci\u00f3n y la bendici\u00f3n", "31": "Josu\u00e9 sucede a Mois\u00e9s", "32": "Mois\u00e9s contempla la tierra de Cana\u00e1n", "33": "Mois\u00e9s bendice a las tribus de Israel", "34": "Muerte y sepultura de Mois\u00e9s"}, "josh": {"1": "Preparativos para la conquista", "2": "Josu\u00e9 env\u00eda esp\u00edas a Jeric\u00f3", "3": "El paso del Jord\u00e1n", "4": "Las doce piedras del Jord\u00e1n", "5": "La circuncisi\u00f3n y la pascua en Gilgal", "6": "La toma de Jeric\u00f3", "7": "El pecado de Ac\u00e1n", "8": "Toma y destrucci\u00f3n de Hai", "9": "Astucia de los gabaonitas", "10": "Derrota de los amorreos", "11": "Derrota de la alianza de Jab\u00edn", "12": "Reyes derrotados por Mois\u00e9s", "13": "Tierra sin conquistar", "14": "Reparto de Cana\u00e1n por suertes", "15": "El territorio de Jud\u00e1", "16": "Territorio de Efra\u00edn y de Manas\u00e9s", "17": "Se echaron a la suerte las tierras para la tribu de Manas\u00e9s, el primer hijo de J", "18": "Territorios de las otras tribus", "19": "A la tribu de los hijos de Sime\u00f3n le toc\u00f3 el reparto del segundo sorteo, conform", "20": "Josu\u00e9 designa ciudades de refugio", "21": "Ciudades de los levitas", "22": "El altar junto al Jord\u00e1n", "23": "Exhortaci\u00f3n de Josu\u00e9 al pueblo", "24": "Discurso de despedida de Josu\u00e9"}, "judg": {"1": "Jud\u00e1 y Sime\u00f3n capturan a Adonib\u00e9sec", "2": "El \u00e1ngel del Se\u00f1or en Boqu\u00edn", "3": "Convivencia de Israel con los pueblos cananeos", "4": "D\u00e9bora y Barac derrotan a S\u00edsara", "5": "C\u00e1ntico de D\u00e9bora y de Barac", "6": "El Se\u00f1or llama a Gede\u00f3n", "7": "Gede\u00f3n derrota a los madianitas", "8": "Gede\u00f3n captura a los reyes de Madi\u00e1n", "9": "Reinado de Abimelec", "10": "Tola y Ya\u00edr acaudillan a Israel", "11": "Jeft\u00e9", "12": "Ibz\u00e1n, El\u00f3n y Abd\u00f3n, jueces de Israel", "13": "Nacimiento de Sans\u00f3n", "14": "Sans\u00f3n y la filistea de Timnat", "15": "Sans\u00f3n derrota a los filisteos en Leh\u00ed", "16": "Sans\u00f3n en Gaza", "17": "Las im\u00e1genes y el sacerdote de Mica\u00eda", "18": "Mica\u00eda y los danitas", "19": "El levita y su concubina", "20": "La guerra contra Benjam\u00edn", "21": "Mujeres para los benjamitas"}, "ruth": {"1": "Rut y Noem\u00ed", "2": "Rut recoge espigas en el campo de Booz", "3": "Rut y Booz en la era", "4": "Booz se casa con Rut"}, "1sam": {"1": "Nacimiento de Samuel", "2": "C\u00e1ntico de Ana", "3": "El Se\u00f1or llama a Samuel", "4": "Los filisteos capturan el arca", "5": "El arca en tierra de los filisteos", "6": "Los filisteos devuelven el arca", "7": "Samuel, juez de Israel", "8": "Israel pide rey", "9": "Sa\u00fal, elegido rey", "10": "Entonces Samuel tom\u00f3 un frasco de aceite y lo derram\u00f3 sobre la cabeza de Sa\u00fal; l", "11": "Sa\u00fal derrota a los amonitas", "12": "Discurso de Samuel al pueblo", "13": "Guerra contra los filisteos", "14": "Entonces Jonat\u00e1n, el hijo de Sa\u00fal, le dijo al criado que le llevaba las armas:", "15": "Sa\u00fal desobedece y es desechado", "16": "Samuel unge a David", "17": "David mata a Goliat", "18": "Pacto de Jonat\u00e1n y David", "19": "Sa\u00fal procura matar a David", "20": "Amistad de David y Jonat\u00e1n", "21": "David huye de Sa\u00fal", "22": "Sa\u00fal mata a los sacerdotes de Nob", "23": "David en el desierto", "24": "David perdona la vida a Sa\u00fal en Engad\u00ed", "25": "David y Abiga\u00edl", "26": "David perdona la vida a Sa\u00fal en Zif", "27": "David entre los filisteos", "28": "Sa\u00fal y la adivina de Endor", "29": "Los filisteos desconf\u00edan de David", "30": "David derrota a los amalecitas", "31": "Muerte de Sa\u00fal y de sus hijos"}, "2sam": {"1": "David se entera de la muerte de Sa\u00fal", "2": "David proclamado rey de Jud\u00e1", "3": "Los hijos de David nacidos en Hebr\u00f3n", "4": "Asesinato de Isboset", "5": "David es proclamado rey de Israel", "6": "David intenta llevar el arca a Jerusal\u00e9n", "7": "Pacto de Dios con David", "8": "David extiende sus dominios", "9": "Bondad de David hacia Mefiboset", "10": "Derrotas de amonitas y sirios", "11": "David y Betsab\u00e9", "12": "Nat\u00e1n amonesta a David", "13": "Amn\u00f3n y Tamar", "14": "Joab promueve el regreso de Absal\u00f3n", "15": "Absal\u00f3n se subleva contra David", "16": "Cuando David lleg\u00f3 m\u00e1s all\u00e1 de la cima del monte, Sib\u00e1, el criado de Mefiboset, ", "17": "Consejos de Ajitofel y de Jusay", "18": "Muerte de Absal\u00f3n", "19": "David vuelve a Jerusal\u00e9n", "20": "Seb\u00e1 se subleva", "21": "Venganza de los gabaonitas", "22": "C\u00e1ntico de liberaci\u00f3n de David", "23": "\u00daltimas palabras de David", "24": "David censa al pueblo"}, "1kgs": {"1": "Abisag sirve a David", "2": "Mandato de David a Salom\u00f3n", "3": "Salom\u00f3n se casa con la hija del fara\u00f3n", "4": "Y Salom\u00f3n fue el rey de todo Israel.", "5": "Pacto de Salom\u00f3n con Jir\u00e1n", "6": "Salom\u00f3n edifica el templo", "7": "Otros edificios de Salom\u00f3n", "8": "Salom\u00f3n lleva el arca al templo", "9": "Pacto del Se\u00f1or con Salom\u00f3n", "10": "La reina de Sab\u00e1 visita a Salom\u00f3n", "11": "Apostas\u00eda de Salom\u00f3n", "12": "Rebeli\u00f3n de Jerobo\u00e1n", "13": "Un profeta de Jud\u00e1 amonesta a Jerobo\u00e1n", "14": "Profec\u00eda de Aj\u00edas contra Jerobo\u00e1n", "15": "Reinado de Ab\u00edas", "16": "Reinado de El\u00e1", "17": "El\u00edas predice la sequ\u00eda", "18": "El\u00edas regresa a ver a Ajab", "19": "El\u00edas huye a Horeb", "20": "Ajab derrota a los sirios", "21": "Ajab y la vi\u00f1a de Nabot", "22": "Mica\u00edas profetiza la derrota de Ajab"}, "2kgs": {"1": "Muerte de Ocoz\u00edas", "2": "Eliseo sucede a El\u00edas", "3": "Reinado de Jor\u00e1n de Israel", "4": "El aceite de la viuda", "5": "Eliseo y Nam\u00e1n", "6": "Eliseo hace flotar el hacha", "7": "Entonces Eliseo dijo:", "8": "La sunamita recupera sus bienes", "9": "Jeh\u00fa es ungido rey de Israel", "10": "Jeh\u00fa pone fin a la dinast\u00eda de Ajab", "11": "Atal\u00eda usurpa el trono", "12": "Reinado de Jo\u00e1s de Jud\u00e1", "13": "Reinado de Joacaz", "14": "Reinado de Amas\u00edas", "15": "Reinado de Azar\u00edas", "16": "Reinado de Ajaz", "17": "Ca\u00edda de Samaria y cautiverio de Israel", "18": "Reinado de Ezequ\u00edas", "19": "Jud\u00e1 es liberado de Senaquerib", "20": "Enfermedad de Ezequ\u00edas", "21": "Reinado de Manas\u00e9s", "22": "Reinado de Jos\u00edas", "23": "Reformas de Jos\u00edas", "24": "Joaqu\u00edn y sus nobles, llevados cautivos a Babilonia", "25": "Ca\u00edda de Jerusal\u00e9n"}, "1chr": {"1": "Descendientes de Ad\u00e1n", "2": "Los hijos de Israel", "3": "Los hijos de David", "4": "Descendientes de Jud\u00e1", "5": "Descendientes de Rub\u00e9n", "6": "Descendientes de Lev\u00ed", "7": "Los descendientes de Isacar", "8": "Los descendientes de Benjam\u00edn", "9": "El retorno de Babilonia", "10": "Muerte de Sa\u00fal y de sus hijos", "11": "David es proclamado rey de Israel", "12": "El ej\u00e9rcito de David", "13": "David propone trasladar el arca a Jerusal\u00e9n", "14": "Jir\u00e1n env\u00eda embajadores a David", "15": "David lleva el arca a Jerusal\u00e9n", "16": "Salmo de acci\u00f3n de gracias", "17": "Pacto de Dios con David", "18": "David extiende sus dominios", "19": "Derrotas de amonitas y sirios", "20": "David captura a Rab\u00e1", "21": "David censa al pueblo", "22": "Preparativos para el templo", "23": "Distribuci\u00f3n y deberes de los levitas", "24": "Tambi\u00e9n los hijos de Aar\u00f3n fueron distribuidos en grupos.", "25": "Distribuci\u00f3n de m\u00fasicos y cantores", "26": "Porteros y oficiales", "27": "Otros oficiales de David", "28": "Salom\u00f3n sucede a David", "29": "Muerte de David"}, "2chr": {"1": "Salom\u00f3n pide sabidur\u00eda", "2": "Pacto de Salom\u00f3n con Jir\u00e1n", "3": "Salom\u00f3n edifica el templo", "4": "Mobiliario del templo", "5": "Salom\u00f3n traslada el arca al templo", "6": "Dedicaci\u00f3n del templo", "7": "Pacto de Dios con Salom\u00f3n", "8": "Otras actividades de Salom\u00f3n", "9": "La reina de Sab\u00e1 visita a Salom\u00f3n", "10": "Rebeli\u00f3n de Israel", "11": "Prosperidad de Robo\u00e1n", "12": "Sisac invade Jud\u00e1", "13": "Reinado de Ab\u00edas", "14": "Reinado de Asa", "15": "Reformas religiosas de Asa", "16": "Alianza de Asa con Ben Adad", "17": "Reinado de Josafat", "18": "Mica\u00edas profetiza la derrota de Ajab", "19": "El profeta Jeh\u00fa amonesta a Josafat", "20": "Victoria sobre Moab y Am\u00f3n", "21": "Reinado de Jor\u00e1n de Jud\u00e1", "22": "Reinado de Ocoz\u00edas de Jud\u00e1", "23": "En el s\u00e9ptimo a\u00f1o Joyad\u00e1 se anim\u00f3 y se ali\u00f3 con los jefes de centenas Azar\u00edas hi", "24": "Reinado de Jo\u00e1s de Jud\u00e1", "25": "Reinado de Amas\u00edas", "26": "Reinado de Uz\u00edas", "27": "Reinado de Yot\u00e1n", "28": "Reinado de Ajaz", "29": "Reinado de Ezequ\u00edas", "30": "Ezequ\u00edas celebra la pascua", "31": "Ezequ\u00edas reorganiza a sacerdotes y levitas", "32": "Senaquerib invade a Jud\u00e1", "33": "Reinado de Manas\u00e9s", "34": "Reinado de Jos\u00edas", "35": "Jos\u00edas celebra la pascua", "36": "Reinado y derrocamiento de Joacaz"}, "ezra": {"1": "El decreto de Ciro", "2": "Los que volvieron con Zorobabel", "3": "Restauraci\u00f3n del altar y del culto", "4": "Los adversarios detienen la obra", "5": "Reedificaci\u00f3n del templo", "6": "Se halla el edicto de Ciro", "7": "Esdras y sus compa\u00f1eros llegan a Jerusal\u00e9n", "8": "\u00c9sta es la lista de las casas patriarcales y la genealog\u00eda de los que durante el", "9": "Oraci\u00f3n de confesi\u00f3n de Esdras", "10": "Expulsi\u00f3n de las mujeres extranjeras"}, "neh": {"1": "Oraci\u00f3n de Nehem\u00edas por Jerusal\u00e9n", "2": "Artajerjes env\u00eda a Nehem\u00edas a Jerusal\u00e9n", "3": "Distribuci\u00f3n de las obras de reconstrucci\u00f3n", "4": "Precauciones contra los enemigos", "5": "Eliminaci\u00f3n de la usura", "6": "Intrigas de los adversarios", "7": "Nehem\u00edas designa dirigentes", "8": "Esdras lee la ley al pueblo", "9": "Esdras confiesa los pecados de Israel", "10": "El pueblo promete obedecer la ley", "11": "Los habitantes de Jerusal\u00e9n", "12": "Sacerdotes y levitas", "13": "Reformas de Nehem\u00edas"}, "esth": {"1": "La reina Vasti desaf\u00eda a Asuero", "2": "Ester es proclamada reina", "3": "Am\u00e1n trama la destrucci\u00f3n de los jud\u00edos", "4": "Ester promete interceder por su pueblo", "5": "Ester invita al rey y a Am\u00e1n a un banquete", "6": "Am\u00e1n se ve obligado a honrar a Mardoqueo", "7": "Am\u00e1n es ahorcado", "8": "El decreto a favor de los jud\u00edos", "9": "Los jud\u00edos destruyen a sus enemigos", "10": "Grandeza de Mardoqueo"}, "job": {"1": "Pr\u00f3logo", "2": "En otra ocasi\u00f3n se presentaron ante el Se\u00f1or sus servidores, y tambi\u00e9n lleg\u00f3 Sat", "3": "Queja de Job", "4": "Primera reprensi\u00f3n de Elifaz a Job", "5": "\u00bbGrita cuanto puedas; a ver qui\u00e9n te responde.", "6": "Job responde a Elifaz", "7": "\u00bbNuestra vida en este mundo es de duro trabajo;", "8": "Primera reprensi\u00f3n de Bildad a Job", "9": "Job responde a Bildad", "10": "\u00bb\u00a1Estoy cansado de esta vida!", "11": "Primera reprensi\u00f3n de Sofar a Job", "12": "Job responde a Sofar", "13": "\u00bbCon mis propios ojos he visto todo esto,", "14": "\u00bbTodos los que nacemos de una mujer", "15": "Segunda reprensi\u00f3n de Elifaz a Job", "16": "Segunda respuesta de Job a Elifaz", "17": "\u00bbLa vida se me escapa. Mis d\u00edas se acortan.", "18": "Segunda reprensi\u00f3n de Bildad a Job", "19": "Segunda respuesta de Job a Bildad", "20": "Segunda reprensi\u00f3n de Sofar a Job", "21": "Segunda respuesta de Job a Sofar", "22": "Tercera reprensi\u00f3n de Elifaz a Job", "23": "Tercera respuesta de Job a Elifaz", "24": "\u00bbSi el Todopoderoso sabe todo lo que pasa,", "25": "Tercera reprensi\u00f3n de Bildad a Job", "26": "Tercera respuesta de Job a Bildad", "27": "Tercera reprensi\u00f3n de Sofar a Job", "28": "Elogio de la sabidur\u00eda", "29": "Job contin\u00faa su respuesta", "30": "\u00bbPero hoy tengo que soportar las burlas", "31": "\u00bbHice un compromiso con mis ojos", "32": "La juventud interviene", "33": "\u00bbTe ruego, Job, que pongas atenci\u00f3n", "34": "Segundo discurso de Eli\u00fa", "35": "Tercer discurso de Eli\u00fa", "36": "Cuarto discurso de Eli\u00fa", "37": "\u00bbAl pensar en esto, mi coraz\u00f3n se acelera", "38": "El Se\u00f1or responde a Job", "39": "\u00bb\u00bfSabes t\u00fa cu\u00e1ndo paren las cabras del monte?", "40": "El Se\u00f1or desaf\u00eda a Job", "41": "\u00bb\u00bfAcaso puedes pescar a Leviat\u00e1n con anzuelo?", "42": "Job reconoce su atrevimiento"}, "ps": {"1": "El justo y los pecadores", "2": "El reino del ungido del Se\u00f1or", "3": "Oraci\u00f3n matutina de confianza en Dios", "4": "Oraci\u00f3n vespertina de confianza en Dios", "5": "Plegaria pidiendo protecci\u00f3n", "6": "Oraci\u00f3n que pide misericordia en tiempos de prueba", "7": "Plegaria pidiendo vindicaci\u00f3n", "8": "La gloria de Dios y la honra del hombre", "9": "Acci\u00f3n de gracias por la justicia de Dios", "10": "Plegaria que pide la destrucci\u00f3n de los malvados", "11": "El refugio del justo", "12": "Oraci\u00f3n que pide ayuda contra los malvados", "13": "Plegaria que pide ayuda en la aflicci\u00f3n", "14": "Insensatez y maldad humana", "15": "Para habitar en el monte de Dios", "16": "Una herencia escogida", "17": "Plegaria que pide la protecci\u00f3n de Dios", "18": "Acci\u00f3n de gracias por la victoria", "19": "Las obras y la palabra de Dios", "20": "Oraci\u00f3n en que se pide la victoria", "21": "Alabanza por haber sido librado del enemigo", "22": "Grito de angustia y canto de alabanza", "23": "El Se\u00f1or es mi pastor", "24": "El rey de gloria", "25": "David implora direcci\u00f3n, perd\u00f3n y protecci\u00f3n", "26": "Declaraci\u00f3n de integridad", "27": "El Se\u00f1or es mi luz y mi salvaci\u00f3n", "28": "Plegaria y alabanza", "29": "Poder y gloria del Se\u00f1or", "30": "Acci\u00f3n de gracias por haber sido librado de la muerte", "31": "Declaraci\u00f3n de confianza", "32": "La dicha del perd\u00f3n", "33": "Alabanzas al Creador", "34": "La protecci\u00f3n divina", "35": "Plegaria pidiendo ser librado de los enemigos", "36": "La misericordia de Dios", "37": "El camino de los malos", "38": "Oraci\u00f3n de un penitente", "39": "Pasamos como una sombra", "40": "Plegaria por la liberaci\u00f3n divina", "41": "Oraci\u00f3n por la salud", "42": "Sed de Dios", "43": "S\u00faplica de liberaci\u00f3n", "44": "Pasado y presente de Israel", "45": "C\u00e1ntico para las bodas del rey", "46": "Dios es nuestro amparo y fortaleza", "47": "Dios, el Rey de toda la tierra", "48": "La gloriosa hermosura de Si\u00f3n", "49": "Es in\u00fatil confiar en las riquezas", "50": "Dios, el Juez supremo", "51": "Plegaria de un pecador", "52": "Jactancia futil del malvado", "53": "Insensatez y maldad humana", "54": "Plegaria por la protecci\u00f3n de Dios", "55": "Contra los amigos falsos y traicioneros", "56": "Oraci\u00f3n de confianza", "57": "Confianza en la ayuda de Dios", "58": "\u00a1Hay un Dios que juzga!", "59": "Dios es nuestra fortaleza", "60": "Plegaria pidiendo ayuda contra el enemigo", "61": "Confianza en la protecci\u00f3n de Dios", "62": "Dios, el \u00fanico refugio", "63": "S\u00f3lo Dios satisface al alma", "64": "Plegaria pidiendo protecci\u00f3n contra enemigos ocultos", "65": "La bondad de Dios en la naturaleza", "66": "Alabanza por los portentos de Dios", "67": "Exhortaci\u00f3n a la alabanza universal", "68": "El Dios del Sina\u00ed y del santuario", "69": "Un grito de angustia", "70": "S\u00faplica de liberaci\u00f3n", "71": "Oraci\u00f3n de un anciano", "72": "El reinado de un rey justo", "73": "El destino de los malos", "74": "S\u00faplica en contra del enemigo", "75": "Exaltaci\u00f3n del justo y humillaci\u00f3n del malvado", "76": "El Dios de la victoria y del juicio", "77": "Evocaci\u00f3n de los portentos de Dios", "78": "Fidelidad de Dios hacia su pueblo infiel", "79": "Lamento por la destrucci\u00f3n de Jerusal\u00e9n", "80": "S\u00faplica por la restauraci\u00f3n", "81": "Bondad de Dios y perversidad de Israel", "82": "Dios, el juez supremo", "83": "Plegaria contra los enemigos de Israel", "84": "Nostalgia por el templo de Dios", "85": "S\u00faplica por la restauraci\u00f3n de Israel", "86": "S\u00faplica por la continua misericordia de Dios", "87": "El privilegio de vivir en Si\u00f3n", "88": "S\u00faplica ante una muerte inminente", "89": "Pacto de Dios con David", "90": "Eternidad de Dios y transitoriedad del hombre", "91": "A la sombra del Omnipotente", "92": "Alabanza a la bondad de Dios", "93": "La majestad del Se\u00f1or", "94": "Oraci\u00f3n que reclama venganza", "95": "C\u00e1ntico de alabanza y de adoraci\u00f3n", "96": "C\u00e1ntico de alabanza", "97": "Dominio y poder del Se\u00f1or", "98": "Alabanza a la justicia de Dios", "99": "Alabanza a la santidad del Se\u00f1or", "100": "Invitaci\u00f3n a la gratitud", "101": "Promesa de vivir rectamente", "102": "Oraci\u00f3n de un afligido", "103": "Alabanza por las bendiciones de Dios", "104": "Dios cuida de su creaci\u00f3n", "105": "Maravillas del Se\u00f1or a favor de Israel", "106": "La rebeld\u00eda de Israel", "107": "Dios libra de la aflicci\u00f3n", "108": "Disposici\u00f3n a la alabanza", "109": "Clamor de venganza", "110": "El ungido del Se\u00f1or", "111": "Dios cuida de su pueblo", "112": "Prosperidad del que teme al Se\u00f1or", "113": "La bondad de Dios por los despose\u00eddos", "114": "Recordando el \u00e9xodo", "115": "Dios y los \u00eddolos", "116": "Acci\u00f3n de gracias por la salud", "117": "Alabanza por la misericordia del Se\u00f1or", "118": "Acci\u00f3n de gracias por la salvaci\u00f3n", "119": "Excelencias de la ley de Dios", "120": "Entre la paz y la guerra", "121": "El Se\u00f1or es tu protector", "122": "Oraci\u00f3n por la paz de Jerusal\u00e9n", "123": "S\u00faplica por la bondad de Dios", "124": "Nuestra ayuda viene del Se\u00f1or", "125": "Dios protege a su pueblo", "126": "Oraci\u00f3n por la restauraci\u00f3n", "127": "Los hijos son una bendici\u00f3n", "128": "Las bendiciones del Se\u00f1or", "129": "La justicia del Se\u00f1or", "130": "Esperanza en la salvaci\u00f3n del Se\u00f1or", "131": "Plena confianza en Dios", "132": "La promesa de Dios a David", "133": "El amor fraternal", "134": "Exhortaci\u00f3n a la alabanza", "135": "La grandeza del Se\u00f1or", "136": "La misericordia del Se\u00f1or", "137": "Recuerdos del cautiverio en Babilonia", "138": "La grandeza del Se\u00f1or", "139": "Dios est\u00e1 en todas partes", "140": "S\u00faplica en contra de los perseguidores", "141": "S\u00faplica por la protecci\u00f3n de Dios", "142": "Clamor en medio de la angustia", "143": "S\u00faplica en medio de la angustia", "144": "Oraci\u00f3n por la prosperidad del pueblo", "145": "Alabanza a la grandeza de Dios", "146": "Alabanza a la justicia de Dios", "147": "Alabanza por el retorno del cautiverio", "148": "Exhortaci\u00f3n a la alabanza universal", "149": "Exhortaci\u00f3n a la alabanza", "150": "Exhortaci\u00f3n a alabar a Dios con instrumentos de m\u00fasica"}, "prov": {"1": "Motivo de los proverbios", "2": "Excelencias de la sabidur\u00eda", "3": "Exhortaci\u00f3n a la obediencia", "4": "Ventajas de la sabidur\u00eda", "5": "Advertencia contra la impureza", "6": "Advertencias contra la pereza y la mentira", "7": "Artima\u00f1as de la mujer ajena", "8": "Elogio a la Sabidur\u00eda", "9": "La Sabidur\u00eda y la mujer insensata", "10": "Contraste entre el justo y el malvado", "11": "Al Se\u00f1or le repugnan las pesas falsas,", "12": "El que ama la correcci\u00f3n ama la sabidur\u00eda;", "13": "El hijo sabio sigue el consejo de su padre;", "14": "La mujer sabia edifica su casa,", "15": "La respuesta amable calma la ira;", "16": "Proverbios sobre la vida y la conducta", "17": "Es mejor un mendrugo de pan, en paz,", "18": "El ego\u00edsta s\u00f3lo piensa en s\u00ed mismo,", "19": "Es mejor ser pobre y honrado,", "20": "Beber vino o bebidas embriagantes", "21": "El coraz\u00f3n del rey se bifurca como los r\u00edos,", "22": "Treinta dichos egipcios", "23": "Cuando te sientes a la mesa de un gran se\u00f1or,", "24": "Otros dichos", "25": "Ejemplos pr\u00e1cticos de conducta", "26": "No conviene la nieve en el verano,", "27": "No te ufanes del d\u00eda de ma\u00f1ana,", "28": "Proverbios antit\u00e9ticos", "29": "El que se empecina ante la reprensi\u00f3n", "30": "Las palabras de Agur", "31": "Exhortaci\u00f3n a un rey"}, "eccl": {"1": "Todo es vanidad", "2": "Pens\u00e9 entonces en lo \u00edntimo de mi ser: \u00ab\u00a1Anda, que voy a probar lo que es la ale", "3": "Todo tiene su tiempo", "4": "Dirig\u00ed entonces la mirada hacia tanta violencia que se comete bajo el sol, y pud", "5": "No hagas votos a la ligera", "6": "Tambi\u00e9n he visto bajo el cielo un mal terrible y muy com\u00fan entre los hombres:", "7": "La sabidur\u00eda y la insensatez", "8": "Desigualdades de la vida", "9": "A todo esto dirig\u00ed mi atenci\u00f3n, para concluir lo siguiente: Que la gente sabia y", "10": "Excelencia de la sabidur\u00eda", "11": "Consejos para la juventud", "12": "Deberes del hombre"}, "song": {"1": "La esposa y las doncellas de Jerusal\u00e9n", "2": "Yo soy la rosa de Sar\u00f3n;", "3": "El ensue\u00f1o de la esposa", "4": "El esposo alaba a la esposa", "5": "El tormento de la separaci\u00f3n", "6": "Mutuo encanto del esposo y de la esposa", "7": "\u00a1Cu\u00e1n bellos se ven, princesa,", "8": "El poder del amor"}, "isa": {"1": "Una naci\u00f3n pecadora", "2": "Reinado universal del Se\u00f1or", "3": "Juicio de Dios contra Jud\u00e1 y Jerusal\u00e9n", "4": "El glorioso futuro de Jerusal\u00e9n", "5": "Par\u00e1bola de la vi\u00f1a", "6": "Visi\u00f3n y vocaci\u00f3n de Isa\u00edas", "7": "Mensaje de Isa\u00edas a Ajaz", "8": "El temor del Se\u00f1or", "9": "Nacimiento y reinado del Mes\u00edas", "10": "Asiria, instrumento de Dios", "11": "Reinado del Mes\u00edas", "12": "C\u00e1ntico de acci\u00f3n de gracias", "13": "Profec\u00eda sobre Babilonia", "14": "Escarnio contra el rey de Babilonia", "15": "Profec\u00eda acerca de Moab", "16": "Env\u00eden un cordero al gobernante de la tierra, desde Sela del desierto hasta el m", "17": "Profec\u00eda acerca de Damasco", "18": "Profec\u00eda acerca de Etiop\u00eda", "19": "Profec\u00eda acerca de Egipto", "20": "Asiria conquistar\u00e1 Egipto y Etiop\u00eda", "21": "Profec\u00eda acerca del desierto junto al mar", "22": "Profec\u00eda acerca del valle de la visi\u00f3n", "23": "Profec\u00eda acerca de Tiro", "24": "El Se\u00f1or juzgar\u00e1 a la tierra", "25": "C\u00e1ntico de gratitud al Se\u00f1or", "26": "C\u00e1ntico de confianza en el Se\u00f1or", "27": "Liberaci\u00f3n y retorno de Israel", "28": "Condenaci\u00f3n de Efra\u00edn", "29": "Ariel y sus enemigos", "30": "De Egipto nada puede esperarse", "31": "Los egipcios son hombres, no dioses", "32": "El Rey justo", "33": "El Se\u00f1or traer\u00e1 salvaci\u00f3n", "34": "La ira del Se\u00f1or contra las naciones", "35": "Futuro glorioso de Si\u00f3n", "36": "La invasi\u00f3n de Senaquerib", "37": "Jud\u00e1 es librado de Senaquerib", "38": "Enfermedad de Ezequ\u00edas", "39": "Ezequ\u00edas recibe a los embajadores de Babilonia", "40": "El Se\u00f1or consuela a Si\u00f3n", "41": "Seguridad de Dios para Israel", "42": "El Siervo del Se\u00f1or", "43": "El Se\u00f1or es el \u00fanico Redentor", "44": "El Se\u00f1or es el \u00fanico Dios", "45": "Encargo de Dios para Ciro", "46": "\u00a1Bel cay\u00f3 de rodillas! \u00a1Nebo rod\u00f3 por los suelos! \u00a1Sus im\u00e1genes fueron echadas s", "47": "Veredicto contra Babilonia", "48": "Dios reprende la infidelidad de Israel", "49": "Israel, siervo del Se\u00f1or", "50": "El Se\u00f1or ayuda a quienes conf\u00edan en \u00e9l", "51": "Palabras de consuelo para Si\u00f3n", "52": "Dios librar\u00e1 A Si\u00f3n del cautiverio", "53": "\u00bfQui\u00e9n ha cre\u00eddo a nuestro anuncio?", "54": "El eterno amor del Se\u00f1or por Israel", "55": "Misericordia gratuita para todos", "56": "Promesa de Dios a los que cumplen su pacto", "57": "Condenaci\u00f3n de la idolatr\u00eda de Israel", "58": "El ayuno verdadero", "59": "Confesi\u00f3n del pecado de Israel", "60": "La futura gloria de Si\u00f3n", "61": "Buenas noticias para Si\u00f3n", "62": "Por causa de Si\u00f3n y de Jerusal\u00e9n no callar\u00e9 ni descansar\u00e9, hasta que su justicia", "63": "El d\u00eda de la venganza del Se\u00f1or", "64": "\u00a1C\u00f3mo quisiera que rasgaras los cielos y bajaras! \u00a1Que los montes se derritieran", "65": "Castigo de los rebeldes", "66": "Prosperidad futura de Si\u00f3n"}, "jer": {"1": "Llamamiento y misi\u00f3n de Jerem\u00edas", "2": "El Se\u00f1or y la apostas\u00eda de Israel", "3": "Llamado al arrepentimiento", "4": "Jud\u00e1 ante la amenaza de una invasi\u00f3n", "5": "Impiedad de Jerusal\u00e9n y de Jud\u00e1", "6": "El juicio contra Jerusal\u00e9n y Jud\u00e1", "7": "El culto verdadero", "8": "Lamento sobre Jud\u00e1 y Jerusal\u00e9n", "9": "Amenaza de ruina y de exilio", "10": "Los dioses falsos y el Dios verdadero", "11": "El pacto violado", "12": "Queja de Jerem\u00edas y respuesta de Dios", "13": "La se\u00f1al del cintur\u00f3n podrido", "14": "Mensaje acerca de la sequ\u00eda", "15": "La implacable ira de Dios contra Jud\u00e1", "16": "Sentencia del Se\u00f1or contra Jud\u00e1", "17": "El pecado en el coraz\u00f3n de Jud\u00e1", "18": "La se\u00f1al del alfarero y el barro", "19": "La se\u00f1al de la vasija rota", "20": "Profec\u00eda contra Pasjur", "21": "Jerusal\u00e9n ser\u00e1 destruida", "22": "Profec\u00edas contra los reyes de Jud\u00e1", "23": "Retorno del remanente", "24": "La se\u00f1al de los higos buenos y malos", "25": "Setenta a\u00f1os de desolaci\u00f3n", "26": "Jerem\u00edas recibe amenazas de muerte", "27": "La se\u00f1al de los yugos", "28": "Falsa profec\u00eda de Janan\u00edas", "29": "Carta de Jerem\u00edas a los cautivos", "30": "Dios anuncia el retorno de los cautivos", "31": "El nuevo pacto", "32": "Jerem\u00edas compra el terreno de Janamel", "33": "Restauraci\u00f3n de Jerusal\u00e9n", "34": "Jerem\u00edas amonesta a Sedequ\u00edas", "35": "Obediencia de los recabitas", "36": "El rey quema el rollo", "37": "Jerem\u00edas es encarcelado", "38": "Jerem\u00edas en la cisterna", "39": "Ca\u00edda de Jerusal\u00e9n", "40": "Jerem\u00edas y el remanente con Gedal\u00edas", "41": "En el mes s\u00e9ptimo, Ismael hijo de Netan\u00edas, hijo de Elisama, de la descendencia ", "42": "Mensaje a Johan\u00e1n", "43": "La emigraci\u00f3n a Egipto", "44": "Jerem\u00edas profetiza a los jud\u00edos en Egipto", "45": "Mensaje de Jerem\u00edas a Baruc", "46": "Profec\u00edas acerca de Egipto", "47": "Profec\u00eda acerca de los filisteos", "48": "Profec\u00eda acerca de Moab", "49": "Profec\u00eda acerca de los amonitas", "50": "Profec\u00eda contra Babilonia", "51": "Sentencia del Se\u00f1or contra Babilonia", "52": "Reinado de Sedequ\u00edas"}, "lam": {"1": "Jerusal\u00e9n lamenta su ca\u00edda", "2": "El castigo de Si\u00f3n", "3": "La misericordia de Dios es constante", "4": "La ca\u00edda de Jerusal\u00e9n", "5": "Oraci\u00f3n del pueblo afligido"}, "ezek": {"1": "La visi\u00f3n de la gloria divina", "2": "Llamamiento de Ezequiel", "3": "Israel al cuidado de Ezequiel", "4": "Predicci\u00f3n del sitio de Jerusal\u00e9n", "5": "\u00bbT\u00fa, hijo de hombre, toma un cuchillo afilado o una navaja de barbero, y af\u00e9itat", "6": "Profec\u00eda contra los montes de Israel", "7": "Anuncio del fin", "8": "Visi\u00f3n de las abominaciones en Jerusal\u00e9n", "9": "Visi\u00f3n de la muerte de los culpables", "10": "La gloria de Dios abandona el templo", "11": "Reprensi\u00f3n de los pr\u00edncipes malvados", "12": "Salida de Ezequiel en se\u00f1al del cautiverio", "13": "Condenaci\u00f3n de los falsos profetas", "14": "Castigo contra los id\u00f3latras", "15": "Jerusal\u00e9n, una vid in\u00fatil", "16": "Infidelidad de Jerusal\u00e9n", "17": "Par\u00e1bola de las \u00e1guilas y la vid", "18": "El que peque morir\u00e1", "19": "Lamentaci\u00f3n sobre los pr\u00edncipes de Israel", "20": "Modo de proceder de Dios con Israel", "21": "La espada afilada del Se\u00f1or", "22": "Los pecados de Jerusal\u00e9n", "23": "Las dos hermanas", "24": "Par\u00e1bola de la olla hirviente", "25": "Profec\u00eda contra Am\u00f3n", "26": "Profec\u00eda contra Tiro", "27": "La palabra del Se\u00f1or vino a m\u00ed, y me dijo:", "28": "Profec\u00eda contra Sid\u00f3n", "29": "Profec\u00edas contra Egipto", "30": "La palabra del Se\u00f1or vino a m\u00ed, y me dijo:", "31": "El d\u00eda primero del mes tercero del a\u00f1o und\u00e9cimo, la palabra del Se\u00f1or vino a m\u00ed,", "32": "El d\u00eda primero del mes duod\u00e9cimo del a\u00f1o duod\u00e9cimo, la palabra del Se\u00f1or vino a ", "33": "El deber del atalaya", "34": "Profec\u00eda contra los pastores de Israel", "35": "Profec\u00eda contra el monte de Seir", "36": "Restauraci\u00f3n futura de Israel", "37": "El valle de los huesos secos", "38": "Profec\u00eda contra Gog", "39": "\u00bbT\u00fa, hijo de hombre, profetiza contra Gog y dile que as\u00ed ha dicho Dios el Se\u00f1or:", "40": "La visi\u00f3n del templo", "41": "El hombre me introdujo en el templo, y midi\u00f3 los postes, los cuales med\u00edan seis ", "42": "El hombre me llev\u00f3 luego al atrio exterior que daba hacia el norte, y me llev\u00f3 a", "43": "La gloria del Se\u00f1or llena el templo", "44": "El hombre me hizo volver hacia la puerta exterior del santuario, la cual da haci", "45": "\u00bbCuando ustedes hagan el sorteo para dar a cada uno su propia tierra, deber\u00e1n ap", "46": "As\u00ed ha dicho Dios el Se\u00f1or:", "47": "El agua saludable", "48": "\u00c9stos son los nombres de las tribus: Dan tendr\u00e1 una parte desde el lado oriental"}, "dan": {"1": "Daniel y sus compa\u00f1eros en Babilonia", "2": "Daniel interpreta el sue\u00f1o de Nabucodonosor", "3": "Rescatados del horno de fuego", "4": "La locura de Nabucodonosor", "5": "La escritura en la pared", "6": "Daniel en el foso de los leones", "7": "Visi\u00f3n de las cuatro bestias", "8": "Visi\u00f3n del carnero y del macho cabr\u00edo", "9": "Oraci\u00f3n de Daniel por su pueblo", "10": "Visi\u00f3n de Daniel junto al r\u00edo", "11": "Los reyes del norte y del sur", "12": "El tiempo del fin"}, "hos": {"1": "Oseas, su esposa infiel y sus hijos", "2": "El amor del Se\u00f1or por un pueblo infiel", "3": "Oseas y la ad\u00faltera", "4": "Controversia del Se\u00f1or con Israel", "5": "Apostas\u00eda y castigo de Israel", "6": "\u00a1Vengan, volvamos nuestros ojos al Se\u00f1or! Ciertamente \u00e9l nos arrebat\u00f3, pero nos ", "7": "Iniquidad y rebeli\u00f3n de Israel", "8": "Reprensi\u00f3n de la idolatr\u00eda de Israel", "9": "La infidelidad de Israel ser\u00e1 castigada", "10": "Israel es una vi\u00f1a frondosa y muy fruct\u00edfera, pero la abundancia de sus frutos f", "11": "Dios se compadece de su obstinado pueblo", "12": "Reprensi\u00f3n de la falsedad y opresi\u00f3n de Efra\u00edn", "13": "Anuncio de la destrucci\u00f3n total de Efra\u00edn", "14": "Israel debe volverse al Se\u00f1or"}, "joel": {"1": "La plaga de langostas", "2": "La misericordia del Se\u00f1or", "3": "Juicio del Se\u00f1or sobre las naciones"}, "amos": {"1": "Juicios contra las naciones vecinas", "2": "Juicio contra Israel", "3": "El rugido del le\u00f3n", "4": "A pesar del castigo, Israel no aprende", "5": "Llamado al arrepentimiento", "6": "Destrucci\u00f3n de Israel", "7": "Tres visiones de destrucci\u00f3n", "8": "El cesto con fruta de verano", "9": "Los ineludibles juicios del Se\u00f1or"}, "obad": {"1": "La humillaci\u00f3n de Edom"}, "jonah": {"1": "Jon\u00e1s huye de Dios", "2": "Oraci\u00f3n de Jon\u00e1s", "3": "N\u00ednive se arrepiente", "4": "El enojo de Jon\u00e1s"}, "mic": {"1": "La palabra del Se\u00f1or vino a Miqueas de Moreset durante el reinado de Yot\u00e1n, Ajaz", "2": "\u00a1Ay de los que oprimen a los pobres!", "3": "Acusaci\u00f3n contra los dirigentes de Israel", "4": "Reinado universal del Se\u00f1or", "5": "El reinado del libertador desde Bel\u00e9n", "6": "Controversia del Se\u00f1or contra Israel", "7": "Corrupci\u00f3n moral de Israel"}, "nah": {"1": "Anuncio de la ca\u00edda de N\u00ednive", "2": "Destrucci\u00f3n total de N\u00ednive", "3": "\u00ab\u00a1Ay de ti, ciudad sanguinaria!"}, "hab": {"1": "Habacuc se queja de la injusticia", "2": "El Se\u00f1or responde a Habacuc", "3": "Oraci\u00f3n de Habacuc"}, "zeph": {"1": "El d\u00eda de la ira del Se\u00f1or", "2": "Juicios contra las naciones vecinas", "3": "Pecado y redenci\u00f3n de Jerusal\u00e9n"}, "hag": {"1": "Exhortaci\u00f3n a edificar el templo", "2": "La gloria del nuevo templo"}, "zech": {"1": "Llamamiento a volverse al Se\u00f1or", "2": "Llamamiento a los cautivos", "3": "Visi\u00f3n del sumo sacerdote Josu\u00e9", "4": "El candelabro de oro y los olivos", "5": "El rollo en vuelo", "6": "Los cuatro carros", "7": "El ayuno que Dios no aprueba", "8": "Dios promete restaurar a Jerusal\u00e9n", "9": "El castigo para las naciones vecinas", "10": "El Se\u00f1or salvar\u00e1 a su pueblo", "11": "Los pastores in\u00fatiles", "12": "Liberaci\u00f3n futura de Jerusal\u00e9n", "13": "El pastor del Se\u00f1or ser\u00e1 herido", "14": "Jerusal\u00e9n y las naciones"}, "mal": {"1": "El amor del Se\u00f1or por Jacob", "2": "Reprensi\u00f3n de la infidelidad de Israel", "3": "El pago de los diezmos", "4": "La llegada del d\u00eda del Se\u00f1or"}, "matt": {"1": "Genealog\u00eda de Jesucristo", "2": "La visita de los sabios", "3": "Predicaci\u00f3n de Juan el Bautista", "4": "Tentaci\u00f3n de Jes\u00fas", "5": "El Serm\u00f3n del monte: Las bienaventuranzas", "6": "Jes\u00fas y la limosna", "7": "El juzgar a los dem\u00e1s", "8": "Jes\u00fas sana a un leproso", "9": "Jes\u00fas sana a un paral\u00edtico", "10": "Elecci\u00f3n de los doce ap\u00f3stoles", "11": "Los mensajeros de Juan el Bautista", "12": "Los disc\u00edpulos recogen espigas en el d\u00eda de reposo", "13": "Par\u00e1bola del sembrador", "14": "Muerte de Juan el Bautista", "15": "La verdadera contaminaci\u00f3n", "16": "La demanda de una se\u00f1al", "17": "La transfiguraci\u00f3n", "18": "\u00bfQui\u00e9n es el mayor?", "19": "Jes\u00fas ense\u00f1a sobre el divorcio", "20": "La vi\u00f1a y los vi\u00f1adores", "21": "La entrada triunfal en Jerusal\u00e9n", "22": "Par\u00e1bola de la fiesta de bodas", "23": "Jes\u00fas acusa a escribas y fariseos", "24": "Jes\u00fas predice la destrucci\u00f3n del templo", "25": "Par\u00e1bola de las diez v\u00edrgenes", "26": "El complot para prender a Jes\u00fas", "27": "Jes\u00fas ante Pilato", "28": "La resurrecci\u00f3n"}, "mark": {"1": "Predicaci\u00f3n de Juan el Bautista", "2": "Jes\u00fas sana a un paral\u00edtico", "3": "El hombre de la mano atrofiada", "4": "Par\u00e1bola del sembrador", "5": "El endemoniado geraseno", "6": "Jes\u00fas en Nazaret", "7": "Lo que contamina al hombre", "8": "Alimentaci\u00f3n de los cuatro mil", "9": "La transfiguraci\u00f3n", "10": "Jes\u00fas ense\u00f1a sobre el divorcio", "11": "La entrada triunfal en Jerusal\u00e9n", "12": "Los labradores malvados", "13": "Jes\u00fas predice la destrucci\u00f3n del templo", "14": "El complot para aprehender a Jes\u00fas", "15": "Jes\u00fas ante Pilato", "16": "La resurrecci\u00f3n"}, "luke": {"1": "Dedicatoria a Te\u00f3filo", "2": "Nacimiento de Jes\u00fas", "3": "Predicaci\u00f3n de Juan el Bautista", "4": "Tentaci\u00f3n de Jes\u00fas", "5": "La pesca milagrosa", "6": "Los disc\u00edpulos espigan en el d\u00eda de reposo", "7": "Jes\u00fas sana al siervo de un centuri\u00f3n", "8": "Mujeres que serv\u00edan a Jes\u00fas", "9": "Misi\u00f3n de los doce disc\u00edpulos", "10": "Misi\u00f3n de los setenta y dos", "11": "Jes\u00fas y la oraci\u00f3n", "12": "La levadura de los fariseos", "13": "Arrepi\u00e9ntanse o perecer\u00e1n", "14": "Jes\u00fas sana a un enfermo", "15": "Par\u00e1bola de la oveja perdida", "16": "Par\u00e1bola del mayordomo infiel", "17": "Ocasiones de caer", "18": "Par\u00e1bola de la viuda y el juez injusto", "19": "Jes\u00fas y Zaqueo", "20": "La autoridad de Jes\u00fas", "21": "La ofrenda de la viuda", "22": "El complot para matar a Jes\u00fas", "23": "Jes\u00fas ante Pilato", "24": "La resurrecci\u00f3n"}, "john": {"1": "La Palabra hecha carne", "2": "Las bodas de Can\u00e1", "3": "Jes\u00fas y Nicodemo", "4": "Jes\u00fas y la mujer samaritana", "5": "El paral\u00edtico de Betesda", "6": "Alimentaci\u00f3n de los cinco mil", "7": "Incredulidad de los hermanos de Jes\u00fas", "8": "Jes\u00fas, la luz del mundo", "9": "Jes\u00fas sana a un ciego de nacimiento", "10": "Par\u00e1bola del redil", "11": "Muerte de L\u00e1zaro", "12": "Jes\u00fas es ungido en Betania", "13": "Jes\u00fas lava los pies de sus disc\u00edpulos", "14": "Jes\u00fas, el camino al Padre", "15": "Jes\u00fas, la vid verdadera", "16": "La obra del Esp\u00edritu Santo", "17": "Jes\u00fas ora por sus disc\u00edpulos", "18": "Arresto de Jes\u00fas", "19": "Crucifixi\u00f3n y muerte de Jes\u00fas", "20": "La resurrecci\u00f3n", "21": "Jes\u00fas se aparece a siete de sus disc\u00edpulos"}, "acts": {"1": "La promesa del Esp\u00edritu Santo", "2": "La llegada del Esp\u00edritu Santo", "3": "Curaci\u00f3n de un cojo", "4": "Pedro y Juan ante el concilio", "5": "Anan\u00edas y Safira", "6": "Elecci\u00f3n de siete di\u00e1conos", "7": "Defensa y muerte de Esteban", "8": "Saulo persigue a la iglesia", "9": "Conversi\u00f3n de Saulo", "10": "Pedro y Cornelio", "11": "Informe de Pedro a la iglesia de Jerusal\u00e9n", "12": "Muerte de Jacobo; encarcelamiento de Pedro", "13": "Bernab\u00e9 y Saulo comienzan su primer viaje misionero", "14": "Pablo y Bernab\u00e9 en Iconio", "15": "El concilio en Jerusal\u00e9n", "16": "Timoteo acompa\u00f1a a Pablo y a Silas", "17": "El alboroto en Tesal\u00f3nica", "18": "Pablo en Corinto", "19": "Pablo en \u00c9feso", "20": "Viaje de Pablo a Macedonia y a Grecia", "21": "Viaje de Pablo a Jerusal\u00e9n", "22": "Pablo relata su conversi\u00f3n", "23": "Complot contra Pablo", "24": "Defensa de Pablo ante F\u00e9lix", "25": "Pablo apela a C\u00e9sar", "26": "Defensa de Pablo ante Agripa", "27": "Pablo es enviado a Roma", "28": "Pablo en la isla de Malta"}, "rom": {"1": "Saludo", "2": "El justo juicio de Dios", "3": "No hay justo", "4": "El ejemplo de Abrah\u00e1n", "5": "Resultados de la justificaci\u00f3n", "6": "Muertos al pecado", "7": "Analog\u00eda tomada del matrimonio", "8": "Viviendo en el Esp\u00edritu", "9": "La elecci\u00f3n de Israel", "10": "Hermanos, ciertamente lo que mi coraz\u00f3n anhela, y lo que pido a Dios en oraci\u00f3n ", "11": "El remanente de Israel", "12": "Deberes cristianos", "13": "Todos debemos someternos a las autoridades, pues no hay autoridad que no venga d", "14": "Los d\u00e9biles en la fe", "15": "El evangelio a los no jud\u00edos", "16": "Saludos personales"}, "1cor": {"1": "Saludo", "2": "Proclamaci\u00f3n de Cristo crucificado", "3": "Colaboradores de Dios", "4": "El ministerio de los ap\u00f3stoles", "5": "Un caso de inmoralidad sexual", "6": "Litigios en presencia de los incr\u00e9dulos", "7": "Problemas matrimoniales", "8": "Las ofrendas a los \u00eddolos", "9": "Los derechos de un ap\u00f3stol", "10": "Amonestaciones contra la idolatr\u00eda", "11": "Atav\u00edo de las mujeres", "12": "Dones espirituales", "13": "La preeminencia del amor", "14": "El hablar en lenguas", "15": "La resurrecci\u00f3n de los muertos", "16": "La ofrenda para los santos"}, "2cor": {"1": "Saludo", "2": "Pablo perdona al ofensor", "3": "Ministros del nuevo pacto", "4": "Vivimos por la fe", "5": "El ministerio de la reconciliaci\u00f3n", "6": "Somos templo del Dios viviente", "7": "Regocijo de Pablo ante el arrepentimiento de los corintios", "8": "La ofrenda para los santos", "9": "En cuanto a la ayuda para los santos, no es necesario que yo les escriba;", "10": "Pablo defiende su ministerio", "11": "Sufrimientos de Pablo como ap\u00f3stol", "12": "El aguij\u00f3n en el cuerpo", "13": "Saludos y doxolog\u00eda final"}, "gal": {"1": "Saludo", "2": "Pablo reprende a Pedro en Antioqu\u00eda", "3": "El Esp\u00edritu se recibe por la fe", "4": "Exhortaci\u00f3n contra el volver a la esclavitud", "5": "Firmes en la libertad", "6": "Pablo se glor\u00eda en la cruz de Cristo"}, "eph": {"1": "Saludo", "2": "Salvados por su gracia", "3": "Ministerio de Pablo a los no jud\u00edos", "4": "La unidad del Esp\u00edritu", "5": "P\u00f3rtense como hijos de luz", "6": "La armadura de Dios"}, "phil": {"1": "Saludo", "2": "Humillaci\u00f3n y exaltaci\u00f3n de Cristo", "3": "Prosigo al blanco", "4": "Regoc\u00edjense en el Se\u00f1or siempre"}, "col": {"1": "Saludo", "2": "Plenitud de vida en Cristo", "3": "La vida antigua y la nueva", "4": "Salutaciones finales"}, "1thess": {"1": "Saludo", "2": "Ministerio de Pablo en Tesal\u00f3nica", "3": "Por lo tanto, cuando ya no pudimos soportarlo m\u00e1s, decidimos quedarnos solos en ", "4": "La vida agradable a Dios", "5": "Pablo exhorta a los hermanos"}, "2thess": {"1": "Saludo", "2": "Manifestaci\u00f3n del hombre de pecado", "3": "Que la palabra de Dios sea glorificada"}, "1tim": {"1": "Saludo", "2": "Instrucciones sobre la oraci\u00f3n", "3": "Requisitos de los obispos", "4": "Predicci\u00f3n de la apostas\u00eda", "5": "Deberes hacia los dem\u00e1s", "6": "Piedad y contentamiento"}, "2tim": {"1": "Saludo", "2": "Un buen soldado de Jesucristo", "3": "Car\u00e1cter de los hombres en los postreros d\u00edas", "4": "Predica la palabra"}, "titus": {"1": "Saludo", "2": "Ense\u00f1anza de la sana doctrina", "3": "Justificados por gracia"}, "phlm": {"1": "Saludo"}, "heb": {"1": "Dios ha hablado por su Hijo", "2": "Una salvaci\u00f3n tan grande", "3": "Jes\u00fas, superior a Mois\u00e9s", "4": "Jes\u00fas el gran sumo sacerdote", "5": "Advertencia contra la apostas\u00eda", "6": "Por lo tanto, dejemos a un lado las ense\u00f1anzas elementales acerca de Cristo, y a", "7": "El sacerdocio de Melquisedec", "8": "El mediador de un nuevo pacto", "9": "El sacrificio de Cristo quita el pecado", "10": "Advertencia a los pecadores deliberados", "11": "La fe", "12": "Con la mirada fija en Jes\u00fas", "13": "Deberes cristianos"}, "jas": {"1": "Saludo", "2": "Amonestaci\u00f3n contra la discriminaci\u00f3n", "3": "La lengua", "4": "La amistad con el mundo", "5": "Contra los ricos opresores"}, "1pet": {"1": "Saludo", "2": "La piedra viva", "3": "Deberes conyugales", "4": "Buenos administradores de la gracia de Dios", "5": "Cuidando de la grey de Dios"}, "2pet": {"1": "Saludo", "2": "Falsos profetas y falsos maestros", "3": "El d\u00eda del Se\u00f1or se acerca"}, "1john": {"1": "La palabra de vida", "2": "Cristo, nuestro abogado", "3": "Hijos de Dios", "4": "El Esp\u00edritu de Dios y el esp\u00edritu del anticristo", "5": "La fe que vence al mundo"}, "2john": {"1": "Salutaci\u00f3n"}, "3john": {"1": "Saludo"}, "jude": {"1": "Saludo"}, "rev": {"1": "La revelaci\u00f3n de Jesucristo", "2": "Mensaje a la iglesia de \u00c9feso", "3": "Mensaje a la iglesia de Sardis", "4": "La adoraci\u00f3n celestial", "5": "El rollo y el Cordero", "6": "Los sellos", "7": "Los 144 mil sellados", "8": "El s\u00e9ptimo sello", "9": "Cuando el quinto \u00e1ngel toc\u00f3 su trompeta, vi que una estrella cay\u00f3 del cielo a la", "10": "El \u00e1ngel con el librito", "11": "Los dos testigos", "12": "La mujer y el drag\u00f3n", "13": "Las dos bestias", "14": "El c\u00e1ntico de los 144 000", "15": "Las siete \u00faltimas plagas", "16": "Las copas de ira", "17": "Condenaci\u00f3n de la gran ramera", "18": "La ca\u00edda de Babilonia", "19": "Alabanzas en el cielo", "20": "Los mil a\u00f1os", "21": "Cielo nuevo y tierra nueva", "22": "La inminente venida de Cristo"}}}